{"name":"Balancing","slug":"Balancing","count":1,"postlist":[{"title":"Electrode–skin impedance imbalance measured in the frequency domain","uid":"98c38e13cecbe168a06c3dec7009a5e0","slug":"文献阅读/Electrodeskinimpedanceimbalancemeasuredinthefrequencydomain","date":"2023-10-22T02:22:17.000Z","updated":"2023-10-22T04:18:17.748Z","comments":true,"path":"api/articles/文献阅读/Electrodeskinimpedanceimbalancemeasuredinthefrequencydomain.json","keywords":null,"cover":"/covers/ReadPaper.png","text":"论文基本信息第一作者：Benjamin C. Fortune;Christopher G. Pretty;Chris J. Cameron;Lachlan R. McKenzie;Logan T. Chatfield;Michael P. Hayes 引用格式：[1]Fortun...","link":"","photos":[],"count_time":{"symbolsCount":"3.1k","symbolsTime":"3 mins."},"categories":[{"name":"ReadPaper","slug":"ReadPaper","count":10,"path":"api/categories/ReadPaper.json"}],"tags":[{"name":"Electrode–skin interface","slug":"Electrode–skin-interface","count":1,"path":"api/tags/Electrode–skin-interface.json"},{"name":"Electrode–tissue interface","slug":"Electrode–tissue-interface","count":1,"path":"api/tags/Electrode–tissue-interface.json"},{"name":"Impedance","slug":"Impedance","count":1,"path":"api/tags/Impedance.json"},{"name":"Compensation","slug":"Compensation","count":1,"path":"api/tags/Compensation.json"},{"name":"Balancing","slug":"Balancing","count":1,"path":"api/tags/Balancing.json"},{"name":"Crosstalk","slug":"Crosstalk","count":1,"path":"api/tags/Crosstalk.json"},{"name":"SEMG","slug":"SEMG","count":1,"path":"api/tags/SEMG.json"},{"name":"EMG","slug":"EMG","count":1,"path":"api/tags/EMG.json"}],"author":{"name":"KyrieYoung","slug":"blog-author","avatar":"https://i.postimg.cc/zfJznFjp/sakuragi.jpg","link":"/","description":"Sharping","socials":{"github":"","twitter":"","stackoverflow":"","wechat":"","qq":"","weibo":"","zhihu":"","csdn":"","juejin":"","customs":{"bilibili":{"icon":"/svg/bilibili.svg","link":"https://space.bilibili.com/40754875?spm_id_from=333.1007.0.0"}}}}}]}